Workbook

Sheet README
B2: This file contains the data and calculations for the techno-economic assement case study contained in "Techno-economic analysis and life cycle assessment for the rapid carbonation of beer"
B4: Each tab contains the relavelnt calculations and results for the system of interest. Input parameters from inventory assessment
B6: Cells in the tabs are color coded acoording to:
B8: Legend
B9: Input
B10: Intermediate Calculations
B11: Results
B13: Tab Name | C13: Description
B14: System Parameters | C14: summary of the case study definition and calculations to determine number of carbonation trains required in each system configuration
B15: BGAL CAPEX | C15: energy assessment for baseline system: 62 gallon beer carbonated over 72h in a bubbled bright tank
B16: BGAL OPEX | C16: energy assessment for system utilizing an average of 75% max power demand on the chiller over 72h in a bubbled bright tank. Carbon dioxide assessment for this scenario is identical to baseline
B17: Traditional CAPEX | C17: energy assessment for system utilizing an average of 50% max power demand on the chiller over 72h in a bubbled bright tank. Carbon dioxide assessment for this scenario is identical to baseline
B18: Traditional OPEX | C18: energy assessment for system utilizing an average of 25% max power demand on the chiller over 72h in a bubbled bright tank. Carbon dioxide assessment for this scenario is identical to baseline

Sheet System Parameters
A1: System Size | B1: 15000 | C1: barrel/yr
B2: =B1*31 -> 465000 | C2: gal/yr
A3: Bright Tank Size | B3: 20 | C3: barrel
B4: =B3*31 -> 620 | C4: gallons
A5: Operating Days | B5: 340 | C5: days/yr
A6: Batches/year | B6: =B1/B3 -> 750 | C6: batches/yr
A8: BGAL Flowrate | B8: 1 | C8: gal/min
A9: BGAL Carbonation time | B9: =B4/B8 -> 620 | C9: min
B10: =ROUND(B9/60,2) -> 10.33 | C10: hours
A11: BGAL Turnover | B11: 1 | C11: hours
A12: BGAL Total Time | B12: 1 | C12: days/batch
A13: BGAL Batches per tank | B13: =ROUNDDOWN(B5/B12,0) -> 340 | C13: batches/yr/tank
A14: BGAL Bright Tanks | B14: =ROUNDUP(B6/B13,0) -> 3 | C14: tanks
A16: Traditional Carbonation Time | B16: 3 | C16: days
A17: Traditional Turnover | B17: 1 | C17: hour
A18: Traditional Total Time | B18: 3 | C18: days/batch
A19: Traditional batches per tank | B19: =B5/B18 -> 113.33333 | C19: batches/yr/tank
A20: Traditional bright tanks | B20: =ROUNDUP(B6/B19,0) -> 7 | C20: tanks

Sheet BGAL CAPEX
A1: Equipment | B1: Specifications | C1: Unit Cost | D1: Number | E1: Purchase Price | F1: Shipping Cost | G1: Delivered Cost | H1: Instillation Cost | I1: Total Installed Cost | J1: Source
A2: Bright Tank | B2: 20bbl - Blichmann | C2: 13500 | D2: ='System Parameters'!$B$14 -> 3 | E2: =C2*D2 -> 40500 | F2: =500*D2/2 -> 750 | G2: =E2+F2 -> 41250 | H2: =G2*0.45 -> 18562.5 | I2: =G2+H2 -> 59812.5 | J2: https://www.blichmannengineering.com/product/20-bbl-brite-tank/ | N2: Legend
A3: Pump | B3: 3.4 GPM Peristaltic Pump - GW Kent | C3: 3558.65 | D3: ='System Parameters'!$B$14 -> 3 | E3: =C3*D3 -> 10675.95 | F3: =500*D3/2 -> 750 | G3: =E3+F3 -> 11425.95 | H3: =G3*0.45 -> 5141.6775 | I3: =G3+H3 -> 16567.628 | J3: https://www.gwkent.com/peristaltic-pump-3-4-gpm.html | N3: Input
A4: Pressure Regulator | B4: CGA 320 125 PSIG max pressure | C4: 472.93 | D4: ='System Parameters'!$B$14 -> 3 | E4: =C4*D4 -> 1418.79 | F4: =500*D4/2 -> 750 | G4: =E4+F4 -> 2168.79 | H4: =G4*0.45 -> 975.9555 | I4: =G4+H4 -> 3144.7455 | J4: https://www.grainger.com/category/welding/gas-equipment/gas-regulators-flowmeters/gas-regulators?attrs=Compatible+Gas+Type%7CCarbon+Dioxide&filters=attrs&searchQuery=co2+co2+regulator&sst=4&tv_optin=true | N4: Intermediate Calculations
A5: 3-way valve | B5: 316 SS 1" NPT | C5: 343.8 | D5: ='System Parameters'!$B$14*2 -> 6 | E5: =C5*D5 -> 2062.8 | F5: =500*D5/2 -> 1500 | G5: =E5+F5 -> 3562.8 | H5: =G5*0.45 -> 1603.26 | I5: =G5+H5 -> 5166.06 | J5: https://www.mcmaster.com/products/three-way-valves/pipe-size~1/body-material~316-stainless-steel/ | N5: Results
A6: Filter Housing | B6: Pureplus 10x4.5 Universal Housing | C6: 51.99 | D6: ='System Parameters'!$B$14*4 -> 12 | E6: =C6*D6 -> 623.88 | F6: =500*D6/2 -> 3000 | G6: =E6+F6 -> 3623.88 | H6: =G6*0.45 -> 1630.746 | I6: =G6+H6 -> 5254.626 | J6: https://www.amazon.com/PUREPLUS-Filter-Housing-Universal-Pre-Filtration/dp/B0CN6MY83H/ref=sr_1_1_sspa?crid=3IT29O6X707HO&dib=eyJ2IjoiMSJ9.AgVg-n57nAmoFRQZ6BGL55Eg1OEJHOVxIMGpyHfavssN964-_Bfrja56wQdGXNHK7uCoNwIJCz6N6O19FLvNmWafKozkQwqPFjsBUliHo37t4J0uPnnkzcH0bSFNnS0yucgCxKIh5QLIJCeiGu7xos1l-ZIGp8Qc1YsJfKFB65qV8eAAIQk0N3AtpuU3TqZSR7WuJ-AtLSLnfU4F6TQVjL1RN4JJpi9cIOkqbwPenUc.4iMbA-5-hLAStOaG145eAFPoKcJ81GiGS9kMQd4wrQo&dib_tag=se&keywords=1%22+clear+water+filter+housing+npt&qid=1722019305&sprefix=1+clear+water+filter+housing+n%2Caps%2C116&sr=8-1-spons&sp_csd=d2lkZ2V0TmFtZT1zcF9hdGY&psc=1
A7: Heat Exchanger | B7: Blichmann Heat Exchanger | C7: 592.99 | D7: ='System Parameters'!$B$14 -> 3 | E7: =C7*D7 -> 1778.97 | F7: =500*D7/2 -> 750 | G7: =E7+F7 -> 2528.97 | H7: =G7*0.45 -> 1138.0365 | I7: =G7+H7 -> 3667.0065 | J7: https://www.blichmannengineering.com/product/pro-brewing-chiller/
A8: Nozzle | B8: 303 SS Fogging Nozzle | C8: 60.43 | D8: ='System Parameters'!$B$14*2 -> 6 | E8: =C8*D8 -> 362.58 | F8: =500*D8/2 -> 1500 | G8: =E8+F8 -> 1862.58 | H8: =G8*0.45 -> 838.161 | I8: =G8+H8 -> 2700.741 | J8: https://www.mcmaster.com/4759N14/
A9: Kegging Manifold | B9: 4-Station Keg-filling Manifold | C9: 482 | D9: ='System Parameters'!$B$14 -> 3 | E9: =C9*D9 -> 1446 | F9: =500*D9/2 -> 750 | G9: =E9+F9 -> 2196 | H9: =G9*0.45 -> 988.2 | I9: =G9+H9 -> 3184.2 | J9: https://www.stouttanks.com/keg-manifold.html
A10: Flowmeter | B10: High Temp Flowmeter 3/4 NPT | C10: 148.85 | D10: ='System Parameters'!$B$14*2 -> 6 | E10: =C10*D10 -> 893.1 | F10: =500*D10/2 -> 1500 | G10: =E10+F10 -> 2393.1 | H10: =G10*0.45 -> 1076.895 | I10: =G10+H10 -> 3469.995 | J10: https://www.mcmaster.com/4400K65/
A11: Total Equipment Costs | I11: =SUM(I2:I10) -> 102967.5
A13: TCI
A14: Fixed Capital Investment (FCI) | B14: =I11 -> 102967.5 | C14: USD
A15: Working Capital (WCI) | B15: =B14*0.15 -> 15445.125 | C15: USD | D15: 15% of FCI - accounts for downtime/instillation time and stockpiling resources
A16: Land | B16: 0 | C16: USD | D16: Assume brewery is already built and land was allocated to other operations
A17: Total Capital Investment | B17: =SUM(B14:B16) -> 118412.63 | C17: USD

Sheet BGAL OPEX
A1: Variable Costs | B1: Excludes labor - no additional requirements from other brewing operations
B2: One batch per 2 days (1hr + 1 day for kegging/cleaning/refill); Operations 340 days/year; 226 batches per year per bright tank
A4: Raw Materials | B4: Unit Cost | C4: Quantity per 20 bbl batch | D4: Cost per Batch | E4: Notes | F4: Source
A5: Carbon Dioxide (USD/50lb tank) | B5: 400 | C5: =21.19/(22.7*0.9) -> 1.0372002 | D5: =B5*C5 -> 414.88008 | E5: assume utilize 90% of gas before replacing | F5: https://beveragelements.com/beverage_elements_shop/gas-cylinders-regulators/co2-cylinders/50-lb-co2-cylinder-aluminum-new/?srsltid=AfmBOooUEhMJxu4FtJ4OvRwj0okhM-yZpCFAKBAZ7a9-Y0XwB8wqs_fb
A7: Consumables | B7: Unit Cost | C7: Quantity per 20 bbl batch | D7: Cost per Batch | E7: Notes
A8: 5 micron filter (USD/filter) | B8: =131.8/20 -> 6.59 | C8: 1 | D8: =B8*C8 -> 6.59 | E8: Assume each filter works for 10 2-bbl batches (20bbl) | F8: amazon.com/Aquaboon-Micron-Water-Filter-4-5/dp/B01LZZA5S7/ref=sr_1_5?crid=1E8ZY6XXCABY4&dib=eyJ2IjoiMSJ9._BKjKH2kAG-ULjYabW9-VJDcrkxBV_0zky1OYcCslTfOlqptDXlLNuBHUfcVzZolcpOyAvh1RLIV0zFSnhU9PQLnYf0QL_AwbGQUpQM4R_1Cr7Cq45wmBjWN4H7JY_qrvmKHxVO4F0-2LluxsacsK41tcawLNS8EkgM-Tdfd3mLTIxWxRiluey0Be1GUbMcxbvspxV_6hABcj-DyPZcmIE-gSfbAZmqKLk3jAvkPZAKXfubZ7eqEh4XD66k0x8BPupDrJO4uqKSLYzU936YsmCdZ3LvXh_-knPPeWW4Hvo8.E7i8aPjkAlZvEmS2Z0_EBRbtQD4Pz6iVVaOCoCcaj-k&dib_tag=se&keywords=4.5"+5+micron+water+filter&qid=1722349567&sprefix=4.5+5+micron+water+filt%2Caps%2C113&sr=8-5
A9: 1 micron filter (USD/filter) | B9: =133.2/20 -> 6.66 | C9: 1 | D9: =B9*C9 -> 6.66 | F9: https://www.amazon.com/Aquaboon-Replacement-Filtration-Compatible-HF45-10BLBK10PR/dp/B01LY0XWRU/ref=sxin_16_pa_sp_search_thematic_sspa?content-id=amzn1.sym.5439bf72-3da4-45fb-a22b-ecb711485806%3Aamzn1.sym.5439bf72-3da4-45fb-a22b-ecb711485806&crid=19W291NEGWFUS&cv_ct_cx=2+micron+water+filter&dib=eyJ2IjoiMSJ9.HXXGQfBfoGbUWyNOL5wEQBrGPJe34qqfwoRgKAYwRjI3z_TD92ykYlW-GyLqyTvHxC1wFpj_e-qn-fZsHvNUNg.bEGe4tJmbBMmDW6foH-a0nShOzcFBw10_75meA8VSjg&dib_tag=se&keywords=2+micron+water+filter&pd_rd_i=B01LY0XWRU&pd_rd_r=32b5697f-a529-4fd2-9bda-140f0e725b94&pd_rd_w=5KtSq&pd_rd_wg=Aljd6&pf_rd_p=5439bf72-3da4-45fb-a22b-ecb711485806&pf_rd_r=6P6JBJ1T9NN1WDPYQMZH&qid=1722349664&sbo=RZvfv%2F%2FHxDF%2BO5021pAnSA%3D%3D&sprefix=2+micron+water+filt%2Caps%2C113&sr=1-4-364cf978-ce2a-480a-9bb0-bdb96faa0f61-spons&sp_csd=d2lkZ2V0TmFtZT1zcF9zZWFyY2hfdGhlbWF0aWM&psc=1
C11: Batches per year
A12: Maintenance (USD/year) | B12: =0.02*'BGAL CAPEX'!B14 -> 2059.35 | C12: 750 | D12: =B12/C12 -> 2.7458 | E12: 2% of FCI annually
A14: Utilities | B14: Unit Cost | C14: Quantity per 20 bbl batch
A15: Electricity (USD/kWh) | B15: 0.1149 | C15: 36.2 | D15: =B15*C15 -> 4.15938 | E15: Average commercial electricity price in Iowa | F15: https://www.eia.gov/states/IA/overview
A16: Total Variable Costs (USD/Batch) | D16: =SUM(D5:D15) -> 435.03526
A17: Total Variable Costs (USD/Year) | D17: =D16*750 -> 326276.44
A19: Fixed Costs | C19: Batches per year
A20: Overhead | B20: 0 | C20: 0 | D20: 0 | E20: no additional requirements from other brewing operations
A21: Local Taxes (USD/year) | B21: =0.015*'BGAL CAPEX'!B14 -> 1544.5125 | C21: 750 | D21: =B21/C21 -> 2.05935 | E21: 1.5% FCI
A22: Insurance (USD/year) | B22: =0.006*'BGAL CAPEX'!B14 -> 617.80501 | C22: 750 | D22: =B22/C22 -> 0.82374001 | E22: 0.6% FCI
A23: Total Fixed Costs (USD/Batch) | D23: =SUM(D20:D22) -> 2.88309
A24: Total Fixed Costs (USD/year) | D24: =D23*750 -> 2162.3175
A26: Capital Investment in Year 0 | B26: ='BGAL CAPEX'!B17 -> 118412.63 | C26: USD | D26: 100% out-of-pocket
A27: Annual Depreciation | B27: =B26/10 -> 11841.263 | C27: USD/year | D27: 0% equity financity
A28: Annual Operating Costs | B28: =D17+D24 -> 328438.76 | C28: USD/year
A29: Batch Operating Costs | B29: =B28/750 -> 437.91835 | C29: USD/batch

Sheet Traditional CAPEX
A1: Equipment | B1: Specifications | C1: Unit Cost | D1: Number | E1: Purchase Price | F1: Shipping Cost | G1: Delivered Cost | H1: Instillation Cost | I1: Total Installed Cost | J1: Source
A2: Bright Tank | B2: 20bbl - Blichmann | C2: 13500 | D2: ='System Parameters'!$B$20 -> 7 | E2: =C2*D2 -> 94500 | F2: =500*D2/2 -> 1750 | G2: =E2+F2 -> 96250 | H2: =G2*0.45 -> 43312.5 | I2: =G2+H2 -> 139562.5 | J2: https://www.blichmannengineering.com/product/20-bbl-brite-tank/ | N2: Legend
A3: Pump | B3: 3.4 GPM Peristaltic Pump - GW Kent | C3: 3558.65 | D3: ='System Parameters'!$B$20 -> 7 | E3: =C3*D3 -> 24910.55 | F3: =500*D3/2 -> 1750 | G3: =E3+F3 -> 26660.55 | H3: =G3*0.45 -> 11997.247 | I3: =G3+H3 -> 38657.798 | J3: https://www.gwkent.com/peristaltic-pump-3-4-gpm.html | N3: Input
A4: Pressure Regulator | B4: CGA 320 125 PSIG max pressure | C4: 472.93 | D4: ='System Parameters'!$B$20 -> 7 | E4: =C4*D4 -> 3310.51 | F4: =500*D4/2 -> 1750 | G4: =E4+F4 -> 5060.51 | H4: =G4*0.45 -> 2277.2295 | I4: =G4+H4 -> 7337.7395 | J4: https://www.grainger.com/category/welding/gas-equipment/gas-regulators-flowmeters/gas-regulators?attrs=Compatible+Gas+Type%7CCarbon+Dioxide&filters=attrs&searchQuery=co2+co2+regulator&sst=4&tv_optin=true | N4: Intermediate Calculations
A5: Total Equipment Costs | I5: =SUM(I2:I4) -> 185558.04 | N5: Results
A7: TCI
A8: Fixed Capital Investment (FCI) | B8: =I5 -> 185558.04 | C8: USD
A9: Working Capital (WCI) | B9: =B8*0.15 -> 27833.706 | C9: USD | D9: 15% of FCI - accounts for downtime/instillation time and stockpiling resources
A10: Land | B10: 0 | C10: USD | D10: Assume brewery is already built and land was allocated to other operations
A11: Total Capital Investment | B11: =SUM(B8:B10) -> 213391.74 | C11: USD

Sheet Traditional OPEX
A1: Variable Costs | B1: Excludes labor - no additional requirements from other brewing operations
B2: One batch per 4 days (72 hrs + 1 day for kegging/cleaning/refill); Operations 340 days/year; 85 batches per year per bright tank
A4: Raw Materials | B4: Unit Cost | C4: Quantity per 20 bbl batch | D4: Cost per Batch | E4: Notes | F4: Source
A5: Carbon Dioxide (USD/50lb tank) | B5: 400 | C5: =23.65/(22.7*0.9) -> 1.1576114 | D5: =B5*C5 -> 463.04454 | E5: assume utilize 90% of gas before replacing | F5: https://beveragelements.com/beverage_elements_shop/gas-cylinders-regulators/co2-cylinders/50-lb-co2-cylinder-aluminum-new/?srsltid=AfmBOooUEhMJxu4FtJ4OvRwj0okhM-yZpCFAKBAZ7a9-Y0XwB8wqs_fb
C6: Batches per year
A7: Maintenance (USD/year) | B7: =0.02*'Traditional CAPEX'!B8 -> 3711.1607 | C7: 750 | D7: =B7/C7 -> 4.9482143 | E7: 2% of FCI annually
A9: Utilities | B9: Unit Cost | C9: Quantity per 20 bbl batch
A10: Electricity (USD/kWh) | B10: 0.1149 | C10: 247 | D10: =B10*C10 -> 28.3803 | E10: Average commercial electricity price in Iowa | F10: https://www.eia.gov/states/IA/overview
A11: Total Variable Costs (USD/Batch) | D11: =SUM(D5:D10) -> 496.37306
A12: Total Variable Costs (USD/Year) | D12: =D11*750 -> 372279.79
A14: Fixed Costs | C14: Batches per year
A15: Overhead | B15: 0 | C15: 0 | D15: 0 | E15: no additional requirements from other brewing operations
A16: Local Taxes (USD/year) | B16: =0.015*'Traditional CAPEX'!B8 -> 2783.3706 | C16: 750 | D16: =B16/C16 -> 3.7111607 | E16: 1.5% FCI
A17: Insurance (USD/year) | B17: =0.006*'Traditional CAPEX'!B8 -> 1113.3482 | C17: 750 | D17: =B17/C17 -> 1.4844643 | E17: 0.6% FCI
A18: Total Fixed Costs (USD/Batch) | D18: =SUM(D15:D17) -> 5.195625
A19: Total Fixed Costs (USD/year) | D19: =D18*750 -> 3896.7188
A21: Capital Investment in Year 0 | B21: ='Traditional CAPEX'!B8 -> 185558.04 | C21: USD | D21: 100% out-of-pocket
A22: Annual Depreciation | B22: =B21/10 -> 18555.804 | C22: USD/year | D22: 0% equity financity
A23: Annual Operating Costs | B23: =D12+D19 -> 376176.51 | C23: USD/year
A24: Batch Operating Costs | B24: =B23/750 -> 501.56868 | C24: USD/batch
