Workbook

Sheet README
B2: This file contains the data and calculations for the BGAL configuration techno-economic assessment and sensitivity analyses contained in "Techno-economic analysis and life cycle assessment for the rapid carbonation of beer"
B4: Each tab contains the relavelnt calculations and results for the system of interest. Input parameters from inventory assessment. Capital expenditures reflect the cost to retrotfit an existing bubbled bright tank system
B6: Cells in the tabs are color coded acoording to:
B8: Legend
B9: Input
B10: Intermediate Calculations
B11: Results
B13: Tab Name | C13: Description
B14: Baseline_CAPEX | C14: capital expenditures for the baseline system: 62 gallon beer carbonated at 1 gpm
B15: Baseline_OPEX | C15: operating expenditures for the baseline system: 62 gallon beer carbonated at 1 gpm
B16: 75%Chiller_OPEX | C16: operating costs for system utilizing an average of 75% max power demand on the chiller at 1 gpm flowrate; CAPEX is identical to baseline system
B17: 50%Chiller_OPEX | C17: operating costs for system utilizing an average of 50% max power demand on the chiller at 1 gpm flowrate; CAPEX is identical to baseline system
B18: 25%Chiller_OPEX | C18: operating costs for system utilizing an average of 25% max power demand on the chiller at 1 gpm flowrate; CAPEX is identical to baseline system
B19: 5Barrel_CAPEX | C19: capital expenditures for 5 barrel system: 155 gallon beer carbonated at 1 gpm flowrate; identical to baseline system
B20: 5Barrel_OPEX | C20: operating costs for 5 barrel system: 155 gallon beer carbonated at 1 gpm flowrate
B21: 10Barrel_CAPEX | C21: capital expenditures for 10 barrel system: 310 gallon beer carbonated at 1 gpm flowrate; identical to baseline system
B22: 10Barrel_OPEX | C22: operating costs for 10 barrel system: 310 gallon beer carbonated at 1gpm flowrate
B23: 10Barrel_CAPEX | C23: capital expenditures for 20 barrel system: 620 gallon beer carbonated at 1 gpm flowrate; identical to baseline system
B24: 20Barrel_OPEX | C24: operating costs for 20 barrel system: 620 gallon beer carbonated at 1gpm flowrate
... B27: 0.25GPM_OPEX | C27: operating costs for system at 0.25 gpm flowrate

Sheet Baseline_CAPEX
A1: Equipment | B1: Specifications | C1: Unit Cost | D1: Number | E1: Purchase Price | F1: Shipping Cost | G1: Delivered Cost | H1: Installation Cost | I1: Total Installed Cost
A2: 3-way valve | B2: 316 SS 1" NPT | C2: 343.8 | D2: 2 | E2: =D2*C2 -> 687.6 | F2: 15 | G2: =SUM(E2:F2) -> 702.6 | H2: =G2*0.45 -> 316.17 | I2: =SUM(H2,G2) -> 1018.77 | N2: Legend
A3: Filter Housing | B3: Pureplus 10x4.5 Universal Housing | C3: 51.99 | D3: 4 | E3: =D3*C3 -> 207.96 | F3: 0 | G3: =SUM(E3:F3) -> 207.96 | H3: =G3*0.45 -> 93.582 | I3: =SUM(H3,G3) -> 301.542 | N3: Input
A4: Heat Exchanger | B4: Blichmann Heat Exchanger | C4: 592.99 | D4: 1 | E4: =D4*C4 -> 592.99 | F4: 150 | G4: =SUM(E4:F4) -> 742.99 | H4: =G4*0.45 -> 334.3455 | I4: =SUM(H4,G4) -> 1077.3355 | N4: Intermediate Calculations
A5: Nozzle | B5: 303 SS Fogging Nozzle | C5: 60.43 | D5: 2 | E5: =D5*C5 -> 120.86 | F5: 15 | G5: =SUM(E5:F5) -> 135.86 | H5: =G5*0.45 -> 61.137 | I5: =SUM(H5,G5) -> 196.997 | N5: Results
A6: Kegging Manifold | B6: 4-Station Keg-filling Manifold | C6: 482 | D6: 1 | E6: =D6*C6 -> 482 | F6: 150 | G6: =SUM(E6:F6) -> 632 | H6: =G6*0.45 -> 284.4 | I6: =SUM(H6,G6) -> 916.4
A7: Flowmeter | B7: High Temp Flowmeter 3/4 NPT | C7: 148.85 | D7: 2 | E7: =D7*C7 -> 297.7 | F7: 15 | G7: =SUM(E7:F7) -> 312.7 | H7: =G7*0.45 -> 140.715 | I7: =SUM(H7,G7) -> 453.415
A8: Total Equipment Costs | I8: =SUM(I2:I7) -> 3964.4595
A10: TCI
A11: Fixed Capital Investment (FCI) | B11: =I8 -> 3964.4595 | C11: USD
A12: Working Capital (WCI) | B12: =B11*0.15 -> 594.66892 | C12: USD | D12: 15% of FCI - accounts for downtime/instillation time and stockpiling resources
A13: Land | B13: 0 | C13: USD | D13: Assume brewery is already built and land was allocated to other operations
A14: Total Capital Investment | B14: =SUM(B11:B13) -> 4559.1284 | C14: USD

Sheet Baseline_OPEX
A1: Variable Costs | B1: Excludes labor - no additional requirements from other brewing operations
B2: One batch per 1.5 days (1hr + 1 day for kegging/cleaning/refill); Operations 340 days/year; 226 batches per year per bright tank; Assume baseline 85 batches per year
A4: Raw Materials | B4: Unit Cost | C4: Quantity per 2 bbl batch | D4: Cost per Batch | E4: Notes
A5: Carbon Dioxide (USD/50lb tank) | B5: 400 | C5: =2.12/(22.7*0.9) -> 0.10376897 | D5: =B5*C5 -> 41.507587 | E5: assume utilize 90% of gas before replacing
A7: Consumables | B7: Unit Cost | C7: Quantity per 2 bbl batch | D7: Cost per Batch | E7: Notes
A8: 5 micron filter (USD/filter) | B8: =131.8/20 -> 6.59 | C8: =1/10 -> 0.1 | D8: =B8*C8 -> 0.659 | E8: Assume each filter works for 10 2-bbl batches (20bbl)
A9: 1 micron filter (USD/filter) | B9: =133.2/20 -> 6.66 | C9: =1/10 -> 0.1 | D9: =B9*C9 -> 0.666
C11: Batches per year
A12: Maintenance (USD/year) | B12: =0.02*Baseline_CAPEX!B11 -> 79.28919 | C12: 113 | D12: =B12/C12 -> 0.70167425 | E12: 2% of FCI annually
A14: Utilities | B14: Unit Cost | C14: Quantity per 2 bbl batch
A15: Electricity (USD/kWh) | B15: 0.1149 | C15: 3.62 | D15: =B15*C15 -> 0.415938 | E15: Average commercial electricity price in Iowa
A16: Total Variable Costs (USD/Batch) | D16: =SUM(D5:D15) -> 43.950199
A17: Total Variable Costs (USD/Year) | D17: =D16*113 -> 4966.3725
A19: Fixed Costs | C19: Batches per year
A20: Overhead | B20: 0 | C20: 0 | D20: 0 | E20: no additional requirements from other brewing operations
A21: Local Taxes (USD/year) | B21: =0.015*Baseline_CAPEX!B11 -> 59.466893 | C21: 113 | D21: =B21/C21 -> 0.52625569 | E21: 1.5% FCI
A22: Insurance (USD/year) | B22: =0.006*Baseline_CAPEX!B11 -> 23.786757 | C22: 113 | D22: =B22/C22 -> 0.21050227 | E22: 0.6% FCI
A23: Total Fixed Costs (USD/Batch) | D23: =SUM(D20:D22) -> 0.73675796
A24: Total Fixed Costs (USD/year) | D24: =D23*113 -> 83.253649
A26: Capital Investment in Year 0 | B26: =Baseline_CAPEX!B14 -> 4559.1284 | C26: USD | D26: 100% out-of-pocket
A27: Annual Depreciation | B27: =B26/10 -> 455.91284 | C27: USD/year | D27: 0% equity financity
A28: Batch Depreciation | B28: =B27/113 -> 4.0346269 | C28: USD/batch
A29: Annual Operating Costs | B29: =D17+D24 -> 5049.6262 | C29: USD/year
A31: Batch Operating Costs | B31: =B29/113 -> 44.686957 | C31: USD/Batch

Sheet 75%Chiller_OPEX
A1: Variable Costs | B1: Excludes labor - no additional requirements from other brewing operations
B2: One batch per 2 days (1hr + 1 day for kegging/cleaning/refill); Operations 340 days/year; 170 batches per year per bright tank
A4: Raw Materials | B4: Unit Cost | C4: Quantity per 2 bbl batch | D4: Cost per Batch | E4: Notes
A5: Carbon Dioxide (USD/50lb tank) | B5: 400 | C5: =2.12/(22.7*0.9) -> 0.10376897 | D5: =B5*C5 -> 41.507587 | E5: assume utilize 90% of gas before replacing
A7: Consumables | B7: Unit Cost | C7: Quantity per 2 bbl batch | D7: Cost per Batch | E7: Notes
A8: 5 micron filter (USD/filter) | B8: =131.8/20 -> 6.59 | C8: =1/10 -> 0.1 | D8: =B8*C8 -> 0.659 | E8: Assume each filter works for 10 batches
A9: 1 micron filter (USD/filter) | B9: =133.2/20 -> 6.66 | C9: =1/10 -> 0.1 | D9: =B9*C9 -> 0.666
C11: Batches per year
A12: Maintenance (USD/year) | B12: =0.02*Baseline_CAPEX!B11 -> 79.28919 | C12: 113 | D12: =B12/C12 -> 0.70167425 | E12: 2% of FCI annually
A14: Utilities | B14: Unit Cost | C14: Quantity per 2 bbl batch
A15: Electricity (USD/kWh) | B15: 0.1149 | C15: 2.74 | D15: =B15*C15 -> 0.314826 | E15: Average commercial electricity price in Iowa
A16: Total Variable Costs (USD/Batch) | D16: =SUM(D5:D15) -> 43.849087
A17: Total Variable Costs (USD/Year) | D17: =D16*113 -> 4954.9468
A19: Fixed Costs | C19: Batches per year
A20: Overhead | B20: 0 | C20: 0 | D20: 0 | E20: no additional requirements from other brewing operations
A21: Local Taxes (USD/year) | B21: =0.015*Baseline_CAPEX!B11 -> 59.466893 | C21: 113 | D21: =B21/C21 -> 0.52625569 | E21: 1.5% FCI
A22: Insurance (USD/year) | B22: =0.006*Baseline_CAPEX!B11 -> 23.786757 | C22: 113 | D22: =B22/C22 -> 0.21050227 | E22: 0.6% FCI
A23: Total Fixed Costs (USD/Batch) | D23: =SUM(D20:D22) -> 0.73675796
A24: Total Fixed Costs (USD/year) | D24: =D23*113 -> 83.253649
A26: Capital Investment in Year 0 | B26: =Baseline_CAPEX!B14 -> 4559.1284 | C26: USD | D26: 100% out-of-pocket
A27: Annual Depreciation | B27: =B26/10 -> 455.91284 | C27: USD/year | D27: 0% equity financity
A28: Batch Depreciation | B28: =B27/113 -> 4.0346269 | C28: USD/batch
A29: Annual Operating Costs | B29: =D17+D24 -> 5038.2005 | C29: USD/year
A31: Batch Operating Costs | B31: =B29/113 -> 44.585845 | C31: USD/Batch

Sheet 50%Chiller_OPEX
A1: Variable Costs | B1: Excludes labor - no additional requirements from other brewing operations
B2: One batch per 2 days (1hr + 1 day for kegging/cleaning/refill); Operations 340 days/year; 170 batches per year per bright tank
A4: Raw Materials | B4: Unit Cost | C4: Quantity per 2 bbl batch | D4: Cost per Batch | E4: Notes
A5: Carbon Dioxide (USD/50lb tank) | B5: 400 | C5: =2.12/(22.7*0.9) -> 0.10376897 | D5: =B5*C5 -> 41.507587 | E5: assume utilize 90% of gas before replacing
A7: Consumables | B7: Unit Cost | C7: Quantity per 2 bbl batch | D7: Cost per Batch | E7: Notes
A8: 5 micron filter (USD/filter) | B8: =131.8/20 -> 6.59 | C8: =1/10 -> 0.1 | D8: =B8*C8 -> 0.659 | E8: Assume each filter works for 10 batches
A9: 1 micron filter (USD/filter) | B9: =133.2/20 -> 6.66 | C9: =1/10 -> 0.1 | D9: =B9*C9 -> 0.666
C11: Batches per year
A12: Maintenance (USD/year) | B12: =0.02*Baseline_CAPEX!B11 -> 79.28919 | C12: 113 | D12: =B12/C12 -> 0.70167425 | E12: 2% of FCI annually
A14: Utilities | B14: Unit Cost | C14: Quantity per 2 bbl batch
A15: Electricity (USD/kWh) | B15: 0.1149 | C15: 1.85 | D15: =B15*C15 -> 0.212565 | E15: Average commercial electricity price in Iowa
A16: Total Variable Costs (USD/Batch) | D16: =SUM(D5:D15) -> 43.746826
A17: Total Variable Costs (USD/Year) | D17: =D16*113 -> 4943.3914
A19: Fixed Costs | C19: Batches per year
A20: Overhead | B20: 0 | C20: 0 | D20: 0 | E20: no additional requirements from other brewing operations
A21: Local Taxes (USD/year) | B21: =0.015*Baseline_CAPEX!B11 -> 59.466893 | C21: 113 | D21: =B21/C21 -> 0.52625569 | E21: 1.5% FCI
A22: Insurance (USD/year) | B22: =0.006*Baseline_CAPEX!B11 -> 23.786757 | C22: 113 | D22: =B22/C22 -> 0.21050227 | E22: 0.6% FCI
A23: Total Fixed Costs (USD/Batch) | D23: =SUM(D20:D22) -> 0.73675796
A24: Total Fixed Costs (USD/year) | D24: =D23*113 -> 83.253649
A26: Capital Investment in Year 0 | B26: =Baseline_CAPEX!B14 -> 4559.1284 | C26: USD | D26: 100% out-of-pocket
A27: Annual Depreciation | B27: =B26/10 -> 455.91284 | C27: USD/year | D27: 0% equity financity
A28: Batch Depreciation | B28: =B27/113 -> 4.0346269 | C28: USD/batch
A29: Annual Operating Costs | B29: =D17+D24 -> 5026.645 | C29: USD/year
A31: Batch Operating Costs | B31: =B29/113 -> 44.483584 | C31: USD/Batch

Sheet 25%Chiller_OPEX
A1: Variable Costs | B1: Excludes labor - no additional requirements from other brewing operations
B2: One batch per 2 days (1hr + 1 day for kegging/cleaning/refill); Operations 340 days/year; 170 batches per year per bright tank
A4: Raw Materials | B4: Unit Cost | C4: Quantity per 2 bbl batch | D4: Cost per Batch | E4: Notes
A5: Carbon Dioxide (USD/50lb tank) | B5: 400 | C5: =2.12/(22.7*0.9) -> 0.10376897 | D5: =B5*C5 -> 41.507587 | E5: assume utilize 90% of gas before replacing
A7: Consumables | B7: Unit Cost | C7: Quantity per 2 bbl batch | D7: Cost per Batch | E7: Notes
A8: 5 micron filter (USD/filter) | B8: =131.8/20 -> 6.59 | C8: =1/10 -> 0.1 | D8: =B8*C8 -> 0.659 | E8: Assume each filter works for 10 batches
A9: 1 micron filter (USD/filter) | B9: =133.2/20 -> 6.66 | C9: =1/10 -> 0.1 | D9: =B9*C9 -> 0.666
C11: Batches per year
A12: Maintenance (USD/year) | B12: =0.02*Baseline_CAPEX!B11 -> 79.28919 | C12: 113 | D12: =B12/C12 -> 0.70167425 | E12: 2% of FCI annually
A14: Utilities | B14: Unit Cost | C14: Quantity per 2 bbl batch
A15: Electricity (USD/kWh) | B15: 0.1149 | C15: 0.97 | D15: =B15*C15 -> 0.111453 | E15: Average commercial electricity price in Iowa
A16: Total Variable Costs (USD/Batch) | D16: =SUM(D5:D15) -> 43.645714
A17: Total Variable Costs (USD/Year) | D17: =D16*113 -> 4931.9657
A19: Fixed Costs | C19: Batches per year
A20: Overhead | B20: 0 | C20: 0 | D20: 0 | E20: no additional requirements from other brewing operations
A21: Local Taxes (USD/year) | B21: =0.015*Baseline_CAPEX!B11 -> 59.466893 | C21: 113 | D21: =B21/C21 -> 0.52625569 | E21: 1.5% FCI
A22: Insurance (USD/year) | B22: =0.006*Baseline_CAPEX!B11 -> 23.786757 | C22: 113 | D22: =B22/C22 -> 0.21050227 | E22: 0.6% FCI
A23: Total Fixed Costs (USD/Batch) | D23: =SUM(D20:D22) -> 0.73675796
A24: Total Fixed Costs (USD/year) | D24: =D23*113 -> 83.253649
A26: Capital Investment in Year 0 | B26: =Baseline_CAPEX!B14 -> 4559.1284 | C26: USD | D26: 100% out-of-pocket
A27: Annual Depreciation | B27: =B26/10 -> 455.91284 | C27: USD/year | D27: 0% equity financity
A28: Batch Depreciation | B28: =B27/113 -> 4.0346269 | C28: USD/batch
A29: Annual Operating Costs | B29: =D17+D24 -> 5015.2193 | C29: USD/year
A31: Batch Operating Costs | B31: =B29/113 -> 44.382472 | C31: USD/Batch

Sheet 5Barrel_CAPEX
A1: Equipment | B1: Specifications | C1: Unit Cost | D1: Number | E1: Purchase Price | F1: Shipping Cost | G1: Delivered Cost | H1: Installation Cost | I1: Total Installed Cost
A2: 3-way valve | B2: 316 SS 1" NPT | C2: 343.8 | D2: 2 | E2: =D2*C2 -> 687.6 | F2: 15 | G2: =SUM(E2:F2) -> 702.6 | H2: =G2*0.45 -> 316.17 | I2: =SUM(H2,G2) -> 1018.77 | N2: Legend
A3: Filter Housing | B3: Pureplus 10x4.5 Universal Housing | C3: 51.99 | D3: 4 | E3: =D3*C3 -> 207.96 | F3: 0 | G3: =SUM(E3:F3) -> 207.96 | H3: =G3*0.45 -> 93.582 | I3: =SUM(H3,G3) -> 301.542 | N3: Input
A4: Heat Exchanger | B4: Blichmann Heat Exchanger | C4: 592.99 | D4: 1 | E4: =D4*C4 -> 592.99 | F4: 150 | G4: =SUM(E4:F4) -> 742.99 | H4: =G4*0.45 -> 334.3455 | I4: =SUM(H4,G4) -> 1077.3355 | N4: Intermediate Calculations
A5: Nozzle | B5: 303 SS Fogging Nozzle | C5: 60.43 | D5: 2 | E5: =D5*C5 -> 120.86 | F5: 15 | G5: =SUM(E5:F5) -> 135.86 | H5: =G5*0.45 -> 61.137 | I5: =SUM(H5,G5) -> 196.997 | N5: Results
A6: Kegging Manifold | B6: 4-Station Keg-filling Manifold | C6: 482 | D6: 1 | E6: =D6*C6 -> 482 | F6: 150 | G6: =SUM(E6:F6) -> 632 | H6: =G6*0.45 -> 284.4 | I6: =SUM(H6,G6) -> 916.4
A7: Flowmeter | B7: High Temp Flowmeter 3/4 NPT | C7: 148.85 | D7: 2 | E7: =D7*C7 -> 297.7 | F7: 15 | G7: =SUM(E7:F7) -> 312.7 | H7: =G7*0.45 -> 140.715 | I7: =SUM(H7,G7) -> 453.415
A8: Total Equipment Costs | I8: =SUM(I2:I7) -> 3964.4595
A10: TCI
A11: Fixed Capital Investment (FCI) | B11: =I8 -> 3964.4595 | C11: USD
A12: Working Capital (WCI) | B12: =B11*0.15 -> 594.66892 | C12: USD | D12: 15% of FCI - accounts for downtime/instillation time and stockpiling resources
A13: Land | B13: 0 | C13: USD | D13: Assume brewery is already built and land was allocated to other operations
A14: Total Capital Investment | B14: =SUM(B11:B13) -> 4559.1284 | C14: USD

Sheet 5Barrel_OPEX
A1: Variable Costs | B1: Excludes labor - no additional requirements from other brewing operations
B2: One batch per 2 days (1hr + 1 day for kegging/cleaning/refill); Operations 340 days/year; 170 batches per year per bright tank
A4: Raw Materials | B4: Unit Cost | C4: Quantity per 2 bbl batch | D4: Cost per Batch | E4: Notes
A5: Carbon Dioxide (USD/50lb tank) | B5: 400 | C5: =5.39/(22.7*0.9) -> 0.2638277 | D5: =B5*C5 -> 105.53108 | E5: assume utilize 90% of gas before replacing
A7: Consumables | B7: Unit Cost | C7: Quantity per 5 bbl batch | D7: Cost per Batch | E7: Notes
A8: 5 micron filter (USD/filter) | B8: =131.8/20 -> 6.59 | C8: =5/20 -> 0.25 | D8: =B8*C8 -> 1.6475 | E8: Assume each filter works for 10 2-bbl batches (20bbl)
A9: 1 micron filter (USD/filter) | B9: =133.2/20 -> 6.66 | C9: =5/20 -> 0.25 | D9: =B9*C9 -> 1.665
C11: Batches per year
A12: Maintenance (USD/year) | B12: =0.02*'5Barrel_CAPEX'!B11 -> 79.28919 | C12: 113 | D12: =B12/C12 -> 0.70167425 | E12: 2% of FCI annually
A14: Utilities | B14: Unit Cost | C14: Quantity per 2 bbl batch
A15: Electricity (USD/kWh) | B15: 0.1149 | C15: 9.06 | D15: =B15*C15 -> 1.040994 | E15: Average commercial electricity price in Iowa
A16: Total Variable Costs (USD/Batch) | D16: =SUM(D5:D15) -> 110.58625
A17: Total Variable Costs (USD/Year) | D17: =D16*113 -> 12496.246
A19: Fixed Costs | C19: Batches per year
A20: Overhead | B20: 0 | C20: 0 | D20: 0 | E20: no additional requirements from other brewing operations
A21: Local Taxes (USD/year) | B21: =0.015*'5Barrel_CAPEX'!B11 -> 59.466893 | C21: 113 | D21: =B21/C21 -> 0.52625569 | E21: 1.5% FCI
A22: Insurance (USD/year) | B22: =0.006*'5Barrel_CAPEX'!B11 -> 23.786757 | C22: 113 | D22: =B22/C22 -> 0.21050227 | E22: 0.6% FCI
A23: Total Fixed Costs (USD/Batch) | D23: =SUM(D20:D22) -> 0.73675796
A24: Total Fixed Costs (USD/year) | D24: =D23*113 -> 83.253649
A26: Capital Investment in Year 0 | B26: ='5Barrel_CAPEX'!B14 -> 4559.1284 | C26: USD | D26: 100% out-of-pocket
A27: Annual Depreciation | B27: =B26/10 -> 455.91284 | C27: USD/year | D27: 0% equity financity
A28: Batch Depreciation | B28: =B27/113 -> 4.0346269 | C28: USD/batch
A29: Annual Operating Costs | B29: =D17+D24 -> 12579.5 | C29: USD/year
A31: Batch Operating Costs | B31: =B29/113 -> 111.32301 | C31: USD/Batch

Sheet 10Barrel_CAPEX
A1: Equipment | B1: Specifications | C1: Unit Cost | D1: Number | E1: Purchase Price | F1: Shipping Cost | G1: Delivered Cost | H1: Installation Cost | I1: Total Installed Cost
A2: 3-way valve | B2: 316 SS 1" NPT | C2: 343.8 | D2: 2 | E2: =D2*C2 -> 687.6 | F2: 15 | G2: =SUM(E2:F2) -> 702.6 | H2: =G2*0.45 -> 316.17 | I2: =SUM(H2,G2) -> 1018.77 | N2: Legend
A3: Filter Housing | B3: Pureplus 10x4.5 Universal Housing | C3: 51.99 | D3: 4 | E3: =D3*C3 -> 207.96 | F3: 0 | G3: =SUM(E3:F3) -> 207.96 | H3: =G3*0.45 -> 93.582 | I3: =SUM(H3,G3) -> 301.542 | N3: Input
A4: Heat Exchanger | B4: Blichmann Heat Exchanger | C4: 592.99 | D4: 1 | E4: =D4*C4 -> 592.99 | F4: 150 | G4: =SUM(E4:F4) -> 742.99 | H4: =G4*0.45 -> 334.3455 | I4: =SUM(H4,G4) -> 1077.3355 | N4: Intermediate Calculations
A5: Nozzle | B5: 303 SS Fogging Nozzle | C5: 60.43 | D5: 2 | E5: =D5*C5 -> 120.86 | F5: 15 | G5: =SUM(E5:F5) -> 135.86 | H5: =G5*0.45 -> 61.137 | I5: =SUM(H5,G5) -> 196.997 | N5: Results
A6: Kegging Manifold | B6: 4-Station Keg-filling Manifold | C6: 482 | D6: 1 | E6: =D6*C6 -> 482 | F6: 150 | G6: =SUM(E6:F6) -> 632 | H6: =G6*0.45 -> 284.4 | I6: =SUM(H6,G6) -> 916.4
A7: Flowmeter | B7: High Temp Flowmeter 3/4 NPT | C7: 148.85 | D7: 2 | E7: =D7*C7 -> 297.7 | F7: 15 | G7: =SUM(E7:F7) -> 312.7 | H7: =G7*0.45 -> 140.715 | I7: =SUM(H7,G7) -> 453.415
A8: Total Equipment Costs | I8: =SUM(I2:I7) -> 3964.4595
A10: TCI
A11: Fixed Capital Investment (FCI) | B11: =I8 -> 3964.4595 | C11: USD
A12: Working Capital (WCI) | B12: =B11*0.15 -> 594.66892 | C12: USD | D12: 15% of FCI - accounts for downtime/instillation time and stockpiling resources
A13: Land | B13: 0 | C13: USD | D13: Assume brewery is already built and land was allocated to other operations
A14: Total Capital Investment | B14: =SUM(B11:B13) -> 4559.1284 | C14: USD

Sheet 10Barrel_OPEX
A1: Variable Costs | B1: Excludes labor - no additional requirements from other brewing operations
B2: One batch per 2 days (1hr + 1 day for kegging/cleaning/refill); Operations 340 days/year; 170 batches per year per bright tank
A4: Raw Materials | B4: Unit Cost | C4: Quantity per 2 bbl batch | D4: Cost per Batch | E4: Notes
A5: Carbon Dioxide (USD/50lb tank) | B5: 400 | C5: =10.6/(22.7*0.9) -> 0.51884484 | D5: =B5*C5 -> 207.53793 | E5: assume utilize 90% of gas before replacing
A7: Consumables | B7: Unit Cost | C7: Quantity per 10 bbl batch | D7: Cost per Batch | E7: Notes
A8: 5 micron filter (USD/filter) | B8: =131.8/20 -> 6.59 | C8: =10/20 -> 0.5 | D8: =B8*C8 -> 3.295 | E8: Assume each filter works for 10 2-bbl batches (20bbl)
A9: 1 micron filter (USD/filter) | B9: =133.2/20 -> 6.66 | C9: =10/20 -> 0.5 | D9: =B9*C9 -> 3.33
C11: Batches per year
A12: Maintenance (USD/year) | B12: =0.02*'10Barrel_CAPEX'!B11 -> 79.28919 | C12: 113 | D12: =B12/C12 -> 0.70167425 | E12: 2% of FCI annually
A14: Utilities | B14: Unit Cost | C14: Quantity per 2 bbl batch
A15: Electricity (USD/kWh) | B15: 0.1149 | C15: 18.1 | D15: =B15*C15 -> 2.07969 | E15: Average commercial electricity price in Iowa
A16: Total Variable Costs (USD/Batch) | D16: =SUM(D5:D15) -> 216.9443
A17: Total Variable Costs (USD/Year) | D17: =D16*113 -> 24514.706
A19: Fixed Costs | C19: Batches per year
A20: Overhead | B20: 0 | C20: 0 | D20: 0 | E20: no additional requirements from other brewing operations
A21: Local Taxes (USD/year) | B21: =0.015*'10Barrel_CAPEX'!B11 -> 59.466893 | C21: 113 | D21: =B21/C21 -> 0.52625569 | E21: 1.5% FCI
A22: Insurance (USD/year) | B22: =0.006*'10Barrel_CAPEX'!B11 -> 23.786757 | C22: 113 | D22: =B22/C22 -> 0.21050227 | E22: 0.6% FCI
A23: Total Fixed Costs (USD/Batch) | D23: =SUM(D20:D22) -> 0.73675796
A24: Total Fixed Costs (USD/year) | D24: =D23*113 -> 83.253649
A26: Capital Investment in Year 0 | B26: ='10Barrel_CAPEX'!B14 -> 4559.1284 | C26: USD | D26: 100% out-of-pocket
A27: Annual Depreciation | B27: =B26/10 -> 455.91284 | C27: USD/year | D27: 0% equity financity
A28: Batch Depreciation | B28: =B27/113 -> 4.0346269 | C28: USD/batch
A29: Annual Operating Costs | B29: =D17+D24 -> 24597.959 | C29: USD/year
A31: Batch Operating Costs | B31: =B29/113 -> 217.68106 | C31: USD/Batch

Sheet 20Barrel_CAPEX
A1: Equipment | B1: Specifications | C1: Unit Cost | D1: Number | E1: Purchase Price | F1: Shipping Cost | G1: Delivered Cost | H1: Installation Cost | I1: Total Installed Cost
A2: 3-way valve | B2: 316 SS 1" NPT | C2: 343.8 | D2: 2 | E2: =D2*C2 -> 687.6 | F2: 15 | G2: =SUM(E2:F2) -> 702.6 | H2: =G2*0.45 -> 316.17 | I2: =SUM(H2,G2) -> 1018.77 | N2: Legend
A3: Filter Housing | B3: Pureplus 10x4.5 Universal Housing | C3: 51.99 | D3: 4 | E3: =D3*C3 -> 207.96 | F3: 0 | G3: =SUM(E3:F3) -> 207.96 | H3: =G3*0.45 -> 93.582 | I3: =SUM(H3,G3) -> 301.542 | N3: Input
A4: Heat Exchanger | B4: Blichmann Heat Exchanger | C4: 592.99 | D4: 1 | E4: =D4*C4 -> 592.99 | F4: 150 | G4: =SUM(E4:F4) -> 742.99 | H4: =G4*0.45 -> 334.3455 | I4: =SUM(H4,G4) -> 1077.3355 | N4: Intermediate Calculations
A5: Nozzle | B5: 303 SS Fogging Nozzle | C5: 60.43 | D5: 2 | E5: =D5*C5 -> 120.86 | F5: 15 | G5: =SUM(E5:F5) -> 135.86 | H5: =G5*0.45 -> 61.137 | I5: =SUM(H5,G5) -> 196.997 | N5: Results
A6: Kegging Manifold | B6: 4-Station Keg-filling Manifold | C6: 482 | D6: 1 | E6: =D6*C6 -> 482 | F6: 150 | G6: =SUM(E6:F6) -> 632 | H6: =G6*0.45 -> 284.4 | I6: =SUM(H6,G6) -> 916.4
A7: Flowmeter | B7: High Temp Flowmeter 3/4 NPT | C7: 148.85 | D7: 2 | E7: =D7*C7 -> 297.7 | F7: 15 | G7: =SUM(E7:F7) -> 312.7 | H7: =G7*0.45 -> 140.715 | I7: =SUM(H7,G7) -> 453.415
A8: Total Equipment Costs | I8: =SUM(I2:I7) -> 3964.4595
A10: TCI
A11: Fixed Capital Investment (FCI) | B11: =I8 -> 3964.4595 | C11: USD
A12: Working Capital (WCI) | B12: =B11*0.15 -> 594.66892 | C12: USD | D12: 15% of FCI - accounts for downtime/instillation time and stockpiling resources
A13: Land | B13: 0 | C13: USD | D13: Assume brewery is already built and land was allocated to other operations
A14: Total Capital Investment | B14: =SUM(B11:B13) -> 4559.1284 | C14: USD

Sheet 20Barrel_OPEX
A1: Variable Costs | B1: Excludes labor - no additional requirements from other brewing operations
B2: One batch per 2 days (1hr + 1 day for kegging/cleaning/refill); Operations 340 days/year; 170 batches per year per bright tank
A4: Raw Materials | B4: Unit Cost | C4: Quantity per 2 bbl batch | D4: Cost per Batch | E4: Notes
A5: Carbon Dioxide (USD/50lb tank) | B5: 400 | C5: =21.19/(22.7*0.9) -> 1.0372002 | D5: =B5*C5 -> 414.88008 | E5: assume utilize 90% of gas before replacing
A7: Consumables | B7: Unit Cost | C7: Quantity per 2 bbl batch | D7: Cost per Batch | E7: Notes
A8: 5 micron filter (USD/filter) | B8: =131.8/20 -> 6.59 | C8: =20/20 -> 1 | D8: =B8*C8 -> 6.59 | E8: Assume each filter works for 10 2-bbl batches (20bbl)
A9: 1 micron filter (USD/filter) | B9: =133.2/20 -> 6.66 | C9: =20/20 -> 1 | D9: =B9*C9 -> 6.66
C11: Batches per year
A12: Maintenance (USD/year) | B12: =0.02*'20Barrel_CAPEX'!B11 -> 79.28919 | C12: 113 | D12: =B12/C12 -> 0.70167425 | E12: 2% of FCI annually
A14: Utilities | B14: Unit Cost | C14: Quantity per 2 bbl batch
A15: Electricity (USD/kWh) | B15: 0.1149 | C15: 36.2 | D15: =B15*C15 -> 4.15938 | E15: Average commercial electricity price in Iowa
A16: Total Variable Costs (USD/Batch) | D16: =SUM(D5:D15) -> 432.99113
A17: Total Variable Costs (USD/Year) | D17: =D16*113 -> 48927.998
A19: Fixed Costs | C19: Batches per year
A20: Overhead | B20: 0 | C20: 0 | D20: 0 | E20: no additional requirements from other brewing operations
A21: Local Taxes (USD/year) | B21: =0.015*'20Barrel_CAPEX'!B11 -> 59.466893 | C21: 113 | D21: =B21/C21 -> 0.52625569 | E21: 1.5% FCI
A22: Insurance (USD/year) | B22: =0.006*'20Barrel_CAPEX'!B11 -> 23.786757 | C22: 113 | D22: =B22/C22 -> 0.21050227 | E22: 0.6% FCI
A23: Total Fixed Costs (USD/Batch) | D23: =SUM(D20:D22) -> 0.73675796
A24: Total Fixed Costs (USD/year) | D24: =D23*113 -> 83.253649
A26: Capital Investment in Year 0 | B26: ='20Barrel_CAPEX'!B14 -> 4559.1284 | C26: USD | D26: 100% out-of-pocket
A27: Annual Depreciation | B27: =B26/10 -> 455.91284 | C27: USD/year | D27: 0% equity financity
A28: Batch Depreciation | B28: =B27/113 -> 4.0346269 | C28: USD/batch
A29: Annual Operating Costs | B29: =D17+D24 -> 49011.252 | C29: USD/year
A31: Batch Operating Costs | B31: =B29/113 -> 433.72789 | C31: USD/Batch

Sheet 2GPM_OPEX
A1: Variable Costs | B1: Excludes labor - no additional requirements from other brewing operations
B2: One batch per 2 days (1hr + 1 day for kegging/cleaning/refill); Operations 340 days/year; 170 batches per year per bright tank
A4: Raw Materials | B4: Unit Cost | C4: Quantity per 2 bbl batch | D4: Cost per Batch | E4: Notes
A5: Carbon Dioxide (USD/50lb tank) | B5: 400 | C5: =2.12/(22.7*0.9) -> 0.10376897 | D5: =B5*C5 -> 41.507587 | E5: assume utilize 90% of gas before replacing
A7: Consumables | B7: Unit Cost | C7: Quantity per 2 bbl batch | D7: Cost per Batch | E7: Notes
A8: 5 micron filter (USD/filter) | B8: =131.8/20 -> 6.59 | C8: =1/10 -> 0.1 | D8: =B8*C8 -> 0.659 | E8: Assume each filter works for 10 2-bbl batches (20bbl)
A9: 1 micron filter (USD/filter) | B9: =133.2/20 -> 6.66 | C9: =1/10 -> 0.1 | D9: =B9*C9 -> 0.666
C11: Batches per year
A12: Maintenance (USD/year) | B12: =0.02*Baseline_CAPEX!B11 -> 79.28919 | C12: 113 | D12: =B12/C12 -> 0.70167425 | E12: 2% of FCI annually
A14: Utilities | B14: Unit Cost | C14: Quantity per 2 bbl batch
A15: Electricity (USD/kWh) | B15: 0.1149 | C15: 1.85 | D15: =B15*C15 -> 0.212565 | E15: Average commercial electricity price in Iowa
A16: Total Variable Costs (USD/Batch) | D16: =SUM(D5:D15) -> 43.746826
A17: Total Variable Costs (USD/Year) | D17: =D16*113 -> 4943.3914
A19: Fixed Costs | C19: Batches per year
A20: Overhead | B20: 0 | C20: 0 | D20: 0 | E20: no additional requirements from other brewing operations
A21: Local Taxes (USD/year) | B21: =0.015*Baseline_CAPEX!B11 -> 59.466893 | C21: 113 | D21: =B21/C21 -> 0.52625569 | E21: 1.5% FCI
A22: Insurance (USD/year) | B22: =0.006*Baseline_CAPEX!B11 -> 23.786757 | C22: 113 | D22: =B22/C22 -> 0.21050227 | E22: 0.6% FCI
A23: Total Fixed Costs (USD/Batch) | D23: =SUM(D20:D22) -> 0.73675796
A24: Total Fixed Costs (USD/year) | D24: =D23*113 -> 83.253649
A26: Capital Investment in Year 0 | B26: =Baseline_CAPEX!B14 -> 4559.1284 | C26: USD | D26: 100% out-of-pocket
A27: Annual Depreciation | B27: =B26/10 -> 455.91284 | C27: USD/year | D27: 0% equity financity
A28: Batch Depreciation | B28: =B27/113 -> 4.0346269 | C28: USD/batch
A29: Annual Operating Costs | B29: =D17+D24 -> 5026.645 | C29: USD/year
A31: Batch Operating Costs | B31: =B29/113 -> 44.483584 | C31: USD/Batch

Sheet 0.5GPM_OPEX
A1: Variable Costs | B1: Excludes labor - no additional requirements from other brewing operations
B2: One batch per 2 days (1hr + 1 day for kegging/cleaning/refill); Operations 340 days/year; 170 batches per year per bright tank
A4: Raw Materials | B4: Unit Cost | C4: Quantity per 2 bbl batch | D4: Cost per Batch | E4: Notes
A5: Carbon Dioxide (USD/50lb tank) | B5: 400 | C5: =2.12/(22.7*0.9) -> 0.10376897 | D5: =B5*C5 -> 41.507587 | E5: assume utilize 90% of gas before replacing
A7: Consumables | B7: Unit Cost | C7: Quantity per 2 bbl batch | D7: Cost per Batch | E7: Notes
A8: 5 micron filter (USD/filter) | B8: =131.8/20 -> 6.59 | C8: =1/10 -> 0.1 | D8: =B8*C8 -> 0.659 | E8: Assume each filter works for 10 2-bbl batches (20bbl)
A9: 1 micron filter (USD/filter) | B9: =133.2/20 -> 6.66 | C9: =1/10 -> 0.1 | D9: =B9*C9 -> 0.666
C11: Batches per year
A12: Maintenance (USD/year) | B12: =0.02*Baseline_CAPEX!B11 -> 79.28919 | C12: 113 | D12: =B12/C12 -> 0.70167425 | E12: 2% of FCI annually
A14: Utilities | B14: Unit Cost | C14: Quantity per 2 bbl batch
A15: Electricity (USD/kWh) | B15: 0.1149 | C15: 7.17 | D15: =B15*C15 -> 0.823833 | E15: Average commercial electricity price in Iowa
A16: Total Variable Costs (USD/Batch) | D16: =SUM(D5:D15) -> 44.358094
A17: Total Variable Costs (USD/Year) | D17: =D16*113 -> 5012.4646
A19: Fixed Costs | C19: Batches per year
A20: Overhead | B20: 0 | C20: 0 | D20: 0 | E20: no additional requirements from other brewing operations
A21: Local Taxes (USD/year) | B21: =0.015*Baseline_CAPEX!B11 -> 59.466893 | C21: 113 | D21: =B21/C21 -> 0.52625569 | E21: 1.5% FCI
A22: Insurance (USD/year) | B22: =0.006*Baseline_CAPEX!B11 -> 23.786757 | C22: 113 | D22: =B22/C22 -> 0.21050227 | E22: 0.6% FCI
A23: Total Fixed Costs (USD/Batch) | D23: =SUM(D20:D22) -> 0.73675796
A24: Total Fixed Costs (USD/year) | D24: =D23*113 -> 83.253649
A26: Capital Investment in Year 0 | B26: =Baseline_CAPEX!B14 -> 4559.1284 | C26: USD | D26: 100% out-of-pocket
A27: Annual Depreciation | B27: =B26/10 -> 455.91284 | C27: USD/year | D27: 0% equity financity
A28: Batch Depreciation | B28: =B27/113 -> 4.0346269 | C28: USD/batch
A29: Annual Operating Costs | B29: =D17+D24 -> 5095.7183 | C29: USD/year
A31: Batch Operating Costs | B31: =B29/113 -> 45.094852 | C31: USD/Batch

Sheet 0.25GPM_OPEX
A1: Variable Costs | B1: Excludes labor - no additional requirements from other brewing operations
B2: One batch per 2 days (1hr + 1 day for kegging/cleaning/refill); Operations 340 days/year; 170 batches per year per bright tank
A4: Raw Materials | B4: Unit Cost | C4: Quantity per 2 bbl batch | D4: Cost per Batch | E4: Notes
A5: Carbon Dioxide (USD/50lb tank) | B5: 400 | C5: =2.12/(22.7*0.9) -> 0.10376897 | D5: =B5*C5 -> 41.507587 | E5: assume utilize 90% of gas before replacing
A7: Consumables | B7: Unit Cost | C7: Quantity per 2 bbl batch | D7: Cost per Batch | E7: Notes
A8: 5 micron filter (USD/filter) | B8: =131.8/20 -> 6.59 | C8: =1/10 -> 0.1 | D8: =B8*C8 -> 0.659 | E8: Assume each filter works for 10 2-bbl batches (20bbl)
A9: 1 micron filter (USD/filter) | B9: =133.2/20 -> 6.66 | C9: =1/10 -> 0.1 | D9: =B9*C9 -> 0.666
C11: Batches per year
A12: Maintenance (USD/year) | B12: =0.02*Baseline_CAPEX!B11 -> 79.28919 | C12: 113 | D12: =B12/C12 -> 0.70167425 | E12: 2% of FCI annually
A14: Utilities | B14: Unit Cost | C14: Quantity per 2 bbl batch
A15: Electricity (USD/kWh) | B15: 0.1149 | C15: 14.3 | D15: =B15*C15 -> 1.64307 | E15: Average commercial electricity price in Iowa
A16: Total Variable Costs (USD/Batch) | D16: =SUM(D5:D15) -> 45.177331
A17: Total Variable Costs (USD/Year) | D17: =D16*113 -> 5105.0384
A19: Fixed Costs | C19: Batches per year
A20: Overhead | B20: 0 | C20: 0 | D20: 0 | E20: no additional requirements from other brewing operations
A21: Local Taxes (USD/year) | B21: =0.015*Baseline_CAPEX!B11 -> 59.466893 | C21: 113 | D21: =B21/C21 -> 0.52625569 | E21: 1.5% FCI
A22: Insurance (USD/year) | B22: =0.006*Baseline_CAPEX!B11 -> 23.786757 | C22: 113 | D22: =B22/C22 -> 0.21050227 | E22: 0.6% FCI
A23: Total Fixed Costs (USD/Batch) | D23: =SUM(D20:D22) -> 0.73675796
A24: Total Fixed Costs (USD/year) | D24: =D23*113 -> 83.253649
A26: Capital Investment in Year 0 | B26: =Baseline_CAPEX!B14 -> 4559.1284 | C26: USD | D26: 100% out-of-pocket
A27: Annual Depreciation | B27: =B26/10 -> 455.91284 | C27: USD/year | D27: 0% equity financity
A28: Batch Depreciation | B28: =B27/113 -> 4.0346269 | C28: USD/batch
A29: Annual Operating Costs | B29: =D17+D24 -> 5188.2921 | C29: USD/year
A31: Batch Operating Costs | B31: =B29/113 -> 45.914089 | C31: USD/Batch
